datalad_mihextras/__init__.py
datalad_mihextras/_version.py
datalad_mihextras/export_bagit.py
datalad_mihextras/snakemake.py
datalad_mihextras/snakemake_monkeypatch.py
datalad_mihextras/resources/procedures/cfg_kdenlive.py
datalad_mihextras/tests/__init__.py
datalad_mihextras/tests/test_register.py
datalad_mihextras/tests/test_snakemake.py
datalad_mihextras-0.7.1.dist-info/LICENSE
datalad_mihextras-0.7.1.dist-info/METADATA
datalad_mihextras-0.7.1.dist-info/WHEEL
datalad_mihextras-0.7.1.dist-info/entry_points.txt
datalad_mihextras-0.7.1.dist-info/top_level.txt
datalad_mihextras-0.7.1.dist-info/RECORD
