Metadata-Version: 2.1
Name: datalad-mihextras
Version: 0.7.1
Summary: DataLad extension with special interest functionality or drafts of future additions to DataLad proper
Home-page: https://github.com/mih/datalad-mihextras
Author: Michael Hanke
Author-email: michael.hanke@gmail.com
License: MIT
Classifier: Programming Language :: Python
Classifier: License :: OSI Approved :: BSD License
Classifier: Programming Language :: Python :: 3
Requires-Python: >=3.8
License-File: LICENSE
Requires-Dist: bdbag
Requires-Dist: datalad (>=0.19.0)
Requires-Dist: datalad-next (>=1.0.0b3)
Provides-Extra: devel
Requires-Dist: coverage ; extra == 'devel'
Requires-Dist: pytest ; extra == 'devel'
Requires-Dist: pytest-cov ; extra == 'devel'
Requires-Dist: snakemake ; extra == 'devel'
